{
  "summary": {
    "count": 6,
    "mean": 14261.17,
    "median": 14238.5,
    "std_dev": 5811.53,
    "min": 6032,
    "max": 23668,
    "range": 17636
  },
  "file_results": [
    {
      "file_name": "linear_T0.3_s1.pdf",
      "word_count": 13623,
      "char_count": 79471,
      "status": "success"
    },
    {
      "file_name": "linear_T0.3_s2.pdf",
      "word_count": 10357,
      "char_count": 58988,
      "status": "success"
    },
    {
      "file_name": "linear_T0.3_s3.pdf",
      "word_count": 15076,
      "char_count": 86998,
      "status": "success"
    },
    {
      "file_name": "linear_T0.7_s1.pdf",
      "word_count": 11815,
      "char_count": 67180,
      "status": "success"
    },
    {
      "file_name": "linear_T0.7_s2.pdf",
      "word_count": 18250,
      "char_count": 102458,
      "status": "success"
    },
    {
      "file_name": "linear_T0.7_s3.pdf",
      "word_count": 11391,
      "char_count": 64373,
      "status": "success"
    },
    {
      "file_name": "linear_T0.9_s1.pdf",
      "word_count": 10871,
      "char_count": 62124,
      "status": "success"
    },
    {
      "file_name": "linear_T0.9_s2.pdf",
      "word_count": 19032,
      "char_count": 108264,
      "status": "success"
    },
    {
      "file_name": "linear_T0.9_s3.pdf",
      "word_count": 6032,
      "char_count": 34741,
      "status": "success"
    },
    {
      "file_name": "nonlinear_T0.3_s1.pdf",
      "word_count": 11064,
      "char_count": 62377,
      "status": "success"
    },
    {
      "file_name": "nonlinear_T0.3_s2.pdf",
      "word_count": 7027,
      "char_count": 40143,
      "status": "success"
    },
    {
      "file_name": "nonlinear_T0.3_s3.pdf",
      "word_count": 13401,
      "char_count": 76336,
      "status": "success"
    },
    {
      "file_name": "nonlinear_T0.7_s1.pdf",
      "word_count": 9772,
      "char_count": 56156,
      "status": "success"
    },
    {
      "file_name": "nonlinear_T0.7_s2.pdf",
      "word_count": 9010,
      "char_count": 51961,
      "status": "success"
    },
    {
      "file_name": "nonlinear_T0.7_s3.pdf",
      "word_count": 15999,
      "char_count": 91993,
      "status": "success"
    },
    {
      "file_name": "nonlinear_T0.9_s1.pdf",
      "word_count": 17749,
      "char_count": 102008,
      "status": "success"
    },
    {
      "file_name": "nonlinear_T0.9_s2.pdf",
      "word_count": 10127,
      "char_count": 57223,
      "status": "success"
    },
    {
      "file_name": "nonlinear_T0.9_s3.pdf",
      "word_count": 23668,
      "char_count": 133996,
      "status": "success"
    }
  ],
  "group_stats": {
    "by_structure": {
      "linear": {
        "count": 9,
        "mean": 12938.56,
        "median": 11815,
        "std_dev": 4072.4,
        "min": 6032,
        "max": 19032,
        "range": 13000
      },
      "nonlinear": {
        "count": 9,
        "mean": 13090.78,
        "median": 11064,
        "std_dev": 5237.59,
        "min": 7027,
        "max": 23668,
        "range": 16641
      }
    },
    "by_temperature": {
      "T0.3": {
        "count": 6,
        "mean": 11758,
        "median": 12232.5,
        "std_dev": 2898.74,
        "min": 7027,
        "max": 15076,
        "range": 8049
      },
      "T0.7": {
        "count": 6,
        "mean": 12706.17,
        "median": 11603.0,
        "std_dev": 3643.4,
        "min": 9010,
        "max": 18250,
        "range": 9240
      },
      "T0.9": {
        "count": 6,
        "mean": 14579.83,
        "median": 14310.0,
        "std_dev": 6619.8,
        "min": 6032,
        "max": 23668,
        "range": 17636
      }
    },
    "by_seed": {
      "s1": {
        "count": 6,
        "mean": 12482.33,
        "median": 11439.5,
        "std_dev": 2878.83,
        "min": 9772,
        "max": 17749,
        "range": 7977
      },
      "s2": {
        "count": 6,
        "mean": 12300.5,
        "median": 10242.0,
        "std_dev": 5056.64,
        "min": 7027,
        "max": 19032,
        "range": 12005
      },
      "s3": {
        "count": 6,
        "mean": 14261.17,
        "median": 14238.5,
        "std_dev": 5811.53,
        "min": 6032,
        "max": 23668,
        "range": 17636
      }
    }
  },
  "analysis_timestamp": "/Users/haha/Story"
}