[
    {
        "sentence": "在城市的一个忙碌街角,艾莉丝坐在一家小巧而温馨的咖啡馆里,窗外是一片人流如织的繁华街道.她身着简单而整洁的衣服,微卷的长发垂落在肩头,眼神中透着一丝坚定.艾莉丝的面前放着一本厚厚的设计杂志,这是她追求梦想的灵感来源.奥斯卡坐在她对面,嘴角带着温暖的微笑,双手环绕着一杯冒着热气的咖啡.他总是充满幽默感,不时地讲述一些轻松的笑话,让艾莉丝脸上绽放出笑容.就在这时,亨利和克拉克推门而入,亨利身着一套剪裁得体的西装,眉头微皱,似乎在思考着什么.克拉克则显得格外热情,向奥斯卡和艾莉丝挥手致意.亨利在寻找一种从未体验过的真实感,克拉克试图让他放松心情.四人围坐在一起,咖啡的香气在空气中弥漫,艾莉丝和亨利之间偶尔的目光交流,似乎预示着某种未解的缘分.",
        "need_to_action": 1,
        "actor_list": [
            "艾莉丝",
            "奥斯卡",
            "亨利",
            "克拉克"
        ],
        "dialogue": {
            "艾莉丝": [
                "艾莉丝: 亨利,你看起来有些心事重重,不如告诉我们是什么困扰着你吧,也许我们可以帮你分担一些."
            ],
            "奥斯卡": [
                "奥斯卡: 奥斯卡: 亨利,有时候真实感可能隐藏在你意想不到的地方.或许你该尝试一些新的体验,比如和我们一起去旅行或者参加一些冒险活动.有时候,改变环境能带来新的视角."
            ],
            "亨利": [
                "亨利: 亨利: 谢谢你的关心,艾莉丝.我最近一直在琢磨如何找到一种真实感,一种能够让我感受到自己存在于这个世界的方式."
            ],
            "克拉克": []
        }
    },
    {
        "sentence": "在城市边缘的旧公寓里,艾莉丝忙碌地准备晚餐,厨房狭小而简陋.墙上的油漆已经剥落,窗外的霓虹灯闪烁着微弱的光芒.艾莉丝的手在炉灶上翻炒,心里想着如何才能实现自己的梦想,摆脱贫困的生活.而此时,玛丽莲和贝拉坐在客厅里,玛丽莲时不时对艾莉丝指手画脚,要求她加快速度.贝拉则在一旁不屑地看着她,心里暗暗嫉妒艾莉丝的勤奋和毅力.艾莉丝知道自己在这个家庭中不受待见,但她依然用善良和勤奋面对这一切,希望有一天能改变自己的命运.",
        "need_to_action": 1,
        "actor_list": [
            "艾莉丝",
            "玛丽莲",
            "贝拉"
        ],
        "dialogue": {
            "艾莉丝": [
                "艾莉丝: 玛丽莲,我知道时间有点紧,但我保证很快就能准备好晚餐.希望今晚的菜能让大家满意.",
                "艾莉丝: 艾莉丝: 我明白你的担心,玛丽莲.我会尽快完成的,谢谢你的理解.贝拉,我知道你可能觉得我太过忙碌,但这些努力是为了我未来的梦想.",
                "艾莉丝: 艾莉丝: 我确实感到累,但我相信这份努力终会有回报.希望我们都能在这顿晚餐中找到一点快乐和满足.",
                "艾莉丝: 艾莉丝: 艾莉丝: 我理解你的建议,贝拉.或许我确实需要学会在追求梦想的同时享受生活的小乐趣.感谢你们的耐心,希望我们今晚能一起度过一个愉快的时光."
            ],
            "玛丽莲": [
                "玛丽莲: 玛丽莲: 艾莉丝,我不是故意催你的,只是今晚的晚餐对我来说很重要.希望你能理解.",
                "玛丽莲: 玛丽莲: 艾莉丝,我知道你很努力,但有时候我们也需要休息一下,享受一下生活.希望今晚的晚餐能让我们都开心一点.",
                "玛丽莲: 玛丽莲: 艾莉丝,我知道今晚的晚餐对你来说也很重要,但请记住,不管今晚如何,我们都会支持你.期待看到你实现梦想的那一天."
            ],
            "贝拉": [
                "贝拉: 贝拉: 艾莉丝,总是这样忙个不停,你不觉得累吗？或许放慢脚步也不错.",
                "贝拉: 贝拉: 艾莉丝,我知道你有你的梦想,但有时候我觉得你可以试着享受生活中的小乐趣,而不仅仅是辛苦地工作."
            ]
        }
    },
    {
        "sentence": "在一个阳光明媚的午后,艾莉丝坐在城市边缘的一家小咖啡馆里,望着窗外的景色.她的心情有些沉重,因为家里的负担让她几乎喘不过气来.咖啡馆内的氛围轻松而温暖,墙上挂着几幅精美的画作,空气中弥漫着新鲜咖啡的香气.艾莉丝正低头思索着时,一个身影走了进来.那是菲奥娜,她穿着一身简单却不失优雅的衣服,配上温柔的笑容,让人感到如沐春风.菲奥娜走到艾莉丝面前,递给她一封信,上面印着精美的花纹和一个神秘的标志.‘这是给你的,艾莉丝.’菲奥娜轻声说道,眼中闪烁着期待.坐在艾莉丝旁边的奥斯卡也好奇地望着信封,心中充满了疑问和期待.艾莉丝小心翼翼地拆开信封,里面是一张邀请函,上面写着一个神秘的时尚设计比赛的邀请.艾莉丝的心跳加快,她知道这可能是她摆脱困境,实现梦想的机会.",
        "need_to_action": 1,
        "actor_list": [
            "艾莉丝",
            "菲奥娜",
            "奥斯卡"
        ],
        "dialogue": {
            "艾莉丝": [
                "艾莉丝: 菲奥娜,这是真的吗？我居然收到了这样的邀请！",
                "艾莉丝: 艾莉丝: 我会努力的,这次机会我绝不会错过.我想要用我的设计让大家看到我的潜力."
            ],
            "菲奥娜": [
                "菲奥娜: 菲奥娜: 是的,艾莉丝,我相信你有这个能力.这次比赛不仅是一个展示你的才华的机会,更是一个重新开始的机会."
            ],
            "奥斯卡": [
                "奥斯卡: 奥斯卡: 艾莉丝,这太棒了！这是一个绝佳的机会,你一定要好好把握."
            ]
        }
    },
    {
        "sentence": "艾莉丝站在丽萨的时尚工作室里,四周环绕着琳琅满目的布料、精致的配饰和各种设计图纸.窗外透进的阳光照在她身上,仿佛为她披上了一层金色的光辉.丽萨正在仔细地为艾莉丝量身定制一套礼服,边上的菲奥娜则微笑着注视着这个年轻女孩,仿佛看到了她的潜力和无限的可能性.艾莉丝心中既紧张又兴奋,她知道这次的变身可能就是她梦想实现的起点.丽萨耐心地指导着艾莉丝,告诉她如何在各种场合展现最好的自己,而菲奥娜则不时插入建议,帮助艾莉丝更好地理解这些时尚的精髓.整个工作室弥漫着一种创造的激情和对未来的期待.",
        "need_to_action": 1,
        "actor_list": [
            "艾莉丝",
            "丽萨",
            "菲奥娜"
        ],
        "dialogue": {
            "艾莉丝": [
                "艾莉丝: 丽萨,这里的一切都太美了,我感到非常幸运能够在你的指导下进行这次变身.",
                "艾莉丝: 艾莉丝: 我真的很期待看到最终的成果,感谢你们的支持和鼓励,我会努力展现出最好的一面.",
                "艾莉丝: 艾莉丝: 我会记住你们的建议,选择那些能与我内心呼应的材料.我相信这次的礼服会让我真正展现出自己的个性和魅力.",
                "艾莉丝: 艾莉丝: 我感到无比激动和感恩,有你们在我身边支持我,让我相信自己能够在这条路上走得更远."
            ],
            "丽萨": [
                "丽萨: 丽萨: 艾莉丝,这只是开始,你有无限的潜力可以挖掘,我们会一起让你的梦想成为现实.",
                "丽萨: 丽萨: 我们现在要开始选择一些面料和配饰,这将是决定这套礼服个性的关键时刻.让我们一起探索吧！",
                "丽萨: 丽萨: 我相信这次的礼服不仅仅是外表的改变,而是为你打开一个新的篇章.让我们选择那些能够反映你内心的材料,让你的个性闪耀其中.",
                "丽萨: 丽萨: 艾莉丝,在选择这些材料时,别忘了让它们与你的内心世界相呼应.你的礼服应该是你的一部分,展现出你独特的魅力和个性.",
                "丽萨: 丽萨: 现在让我们来看看这些图纸,我会为你解释每一种设计的风格和它们所传达的情感.选择那些与你心灵产生共鸣的设计,让它们成为你梦想的载体."
            ],
            "菲奥娜": [
                "菲奥娜: 菲奥娜: 艾莉丝,你的一举一动都充满了魅力和可能性.相信自己,我们会在这段旅程中看到你最闪耀的一面.",
                "菲奥娜: 菲奥娜: 艾莉丝,记得时刻保持自信,你的内心力量会让你在任何场合都绽放光彩.我们会一直支持你,一起实现你的梦想."
            ]
        }
    },
    {
        "sentence": "在城市边缘的旧仓库,艾莉丝费力地推开锈迹斑斑的铁门,进入了这个被遗忘的空间.夜幕降临,星光透过破碎的窗户洒在地上,给这片废弃之地增添了一丝神秘.艾莉丝的心中充满了希望与紧张,她知道这一晚可能会改变她的命运.菲奥娜站在仓库角落,身影被星光勾勒出柔和的轮廓,她微笑着迎接这个有潜力的年轻人.她用温柔而坚定的声音鼓励艾莉丝,告诉她今晚将是她的魔法时刻.与此同时,奥斯卡也在场,他始终陪伴在她身边,目光中充满了鼓励和默默的支持.他们共同站在一个巨大的画布前,准备将艾莉丝的梦想变为现实.在菲奥娜的指导下,艾莉丝开始为即将到来的时尚设计比赛做准备,这不仅是一次展示才华的机会,更是实现梦想的起点.",
        "need_to_action": 1,
        "actor_list": [
            "艾莉丝",
            "菲奥娜",
            "奥斯卡"
        ],
        "dialogue": {
            "艾莉丝": [
                "艾莉丝: 菲奥娜,我准备好了,今晚我会全力以赴.谢谢你一直以来的指导和支持.",
                "艾莉丝: 艾莉丝: 我感受到这里的每一丝能量,这个仓库仿佛在诉说着它的故事.",
                "艾莉丝: 艾莉丝: 我会记住你们的每一句话,让它们成为我的动力.现在,让我们开始吧！",
                "艾莉丝: 艾莉丝: 我感受到你们的支持,我会用我的设计给这个仓库新的生命."
            ],
            "菲奥娜": [
                "菲奥娜: 菲奥娜: 艾莉丝,我相信你的潜力.让我们一起创造出令人惊叹的设计吧.",
                "菲奥娜: 菲奥娜: 记住,艾莉丝,艺术是表达内心的窗口.让你的设计成为你灵魂的延伸.",
                "菲奥娜: 菲奥娜: 艾莉丝,记得每一笔都是你的心声,跟随你的直觉,别怕犯错,因为每一个失败都是成功的阶梯.",
                "菲奥娜: 菲奥娜: 艾莉丝,在这片星光下,让你的设计如星辰般闪耀,无论遇到什么困难,我们都会在这里支持着你."
            ],
            "奥斯卡": [
                "奥斯卡: 奥斯卡: 艾莉丝,无论结果如何,你的努力和才华已经证明了一切.今晚,我们将见证你的梦想绽放.",
                "奥斯卡: 奥斯卡: 艾莉丝,这幅画布是你的舞台,让你的创意在这里尽情展现.相信自己,你能做到."
            ]
        }
    },
    {
        "sentence": "午夜时分,城市的喧嚣渐渐平息,月光洒在寂静的公园跑道上,给它披上了一层银色的薄纱.艾莉丝用力地奔跑着,感受着凉风拂过脸庞,仿佛想要甩掉生活的重担与烦恼.她的呼吸急促而坚定,仿佛在追逐那遥不可及的梦想.忽然间,她听到身后传来脚步声,回头一看,是奥斯卡,他总是能在她需要的时候出现,充满鼓励和支持.两人并肩而跑,默契十足.片刻后,亨利出现在跑道的另一边,他在奥斯卡的建议下,尝试用这场夜跑来寻找内心的宁静.他的身影在月光下显得格外挺拔,尽管身为富家子弟,但他渴望的只是简单的快乐和自由.在这片寂静的夜色中,三个人各自带着心中的目标与追求奔跑着,彼此的存在让夜晚显得不再孤单.",
        "need_to_action": 1,
        "actor_list": [
            "艾莉丝",
            "奥斯卡",
            "亨利"
        ],
        "dialogue": {
            "艾莉丝": [
                "艾莉丝: 嘿,奥斯卡,你总是在我最需要的时候出现,真是太不可思议了."
            ],
            "奥斯卡": [
                "奥斯卡: 奥斯卡: 我知道你在追求梦想的路上需要支持,所以我会一直在你身边."
            ],
            "亨利": []
        }
    },
    {
        "sentence": "夜幕低垂,城市中心的豪华酒店灯火辉煌,舞会大厅内流光溢彩.艾莉丝身穿丽萨精心设计的礼服,宛如灰姑娘般优雅地走入会场.她的眼神中流露出一丝紧张与期待,周围的宾客纷纷驻足赞叹她的美丽.亨利站在不远处,目光不自觉地被艾莉丝吸引.他心中升起一股陌生的悸动,仿佛找到了他一直寻找的东西.与此同时,菲奥娜站在一旁,微笑着看着艾莉丝,心中感到欣慰,她知道今晚将是艾莉丝命运的转折点.舞会的乐声响起,亨利走向艾莉丝,邀请她共舞,两人间的化学反应宛如夜空中绽放的烟花,照亮了彼此的内心.",
        "need_to_action": 1,
        "actor_list": [
            "艾莉丝",
            "亨利",
            "菲奥娜"
        ],
        "dialogue": {
            "艾莉丝": [
                "艾莉丝: 亨利,谢谢你的邀请,我有些紧张,但我会尽力而为.",
                "艾莉丝: 艾莉丝: 我会努力做到的,谢谢你们的鼓励,今晚对我来说意义非凡."
            ],
            "亨利": [
                "亨利: 亨利: 别担心,艾莉丝,只要跟随音乐的节奏,让自己放松,你会发现跳舞其实很简单.",
                "亨利: 亨利: 艾莉丝,我相信今晚将是一个美好的开始,让我们一起创造难忘的回忆吧."
            ],
            "菲奥娜": [
                "菲奥娜: 菲奥娜: 艾莉丝,你看起来很美丽,自信地享受这个时刻吧,我相信你会闪耀全场."
            ]
        }
    },
    {
        "sentence": "在城市边缘的一个古老而充满艺术气息的时尚工作室里,艾莉丝紧张地站在镜子前,穿着丽萨精心设计的礼服.房间里弥漫着咖啡和新鲜布料的香味,墙上挂着菲奥娜曾经获奖的设计作品,仿佛在诉说着她辉煌的过去.菲奥娜站在艾莉丝身旁,轻声指导着如何展示自己的风采.窗外,夕阳的余晖洒在亨利的脸上,他凝视着艾莉丝,心中升起一种从未有过的感动.此刻,他意识到自己一直追求的意义或许就在眼前.丽萨细心地调整着艾莉丝的礼服,确保每一个细节都完美无瑕.这个工作室成为了艾莉丝梦想起航的地方,也是她与亨利命运交织的起点.",
        "need_to_action": 1,
        "actor_list": [
            "艾莉丝",
            "菲奥娜",
            "亨利",
            "丽萨"
        ],
        "dialogue": {
            "艾莉丝": [
                "艾莉丝: 这件礼服真的是太美了,丽萨,你的设计让我感到无比自信.菲奥娜,我会记住你的每一个指导.亨利,谢谢你一直在我身边支持我."
            ],
            "菲奥娜": [
                "菲奥娜: 菲奥娜: 艾莉丝,记住要从心底绽放你的光彩,这不仅仅是一件礼服,而是你梦想的载体."
            ],
            "亨利": [
                "亨利: 亨利: 艾莉丝,看到你穿上这件礼服,我才明白支持你的每一步是多么值得.你的光芒让我感到无比震撼."
            ],
            "丽萨": [
                "丽萨: 丽萨: 每一针每一线都是为了让你在舞台上展现最真实的自己,艾莉丝,看到你如此幸福,我觉得所有的努力都值得."
            ]
        }
    },
    {
        "sentence": "在华丽的城市中心,闪烁的霓虹灯将夜色点缀得如梦如幻.时尚秀场内,艾莉丝站在后台,紧张而兴奋地调整着丽萨为她设计的服装.她的梦想即将在此刻实现,心中充满了期待.菲奥娜在一旁,微笑着给予她鼓励,仿佛一位守护者,默默注视着她的成长.前排,亨利坐在观众席中,他的目光追随着即将登场的艾莉丝,心中充满了好奇与期许.随着音乐响起,艾莉丝踏上了T台,灯光打在她的身上,瞬间将她化作全场的焦点.她的步伐坚定,眼神中闪烁着梦想成真的光芒.",
        "need_to_action": 1,
        "actor_list": [
            "艾莉丝",
            "菲奥娜",
            "亨利"
        ],
        "dialogue": {
            "艾莉丝": [
                "艾莉丝: 菲奥娜,谢谢你的鼓励,我感觉自己充满了力量.亨利,我希望我的表现能够让你感到惊艳."
            ],
            "菲奥娜": [
                "菲奥娜: 菲奥娜: 艾莉丝,相信自己的力量,你已经准备好迎接这一刻.我会一直在你身边,支持着你."
            ],
            "亨利": [
                "亨利: 亨利: 艾莉丝,你已经是耀眼的明星了,我迫不及待地想看到你在T台上展现你的光芒."
            ]
        }
    }
]